{
  "fields": [
    {
      "name":"role",
      "label":"Position",
      "required":true,
      "helper_text":"",
      "type":"choices",
      "collection":"roles",
      "order": 1
    },

    {
      "name":"role_other",
      "label":"Please specify",
      "order": 2,
      "required":true,
      "visible_byfield":"role",
      "visible_byvalue":"other",
      "type":"str"
    },
    {
      "name":"gender",
      "label":"Sex",
      "required":false,
      "helper_text":"",
      "type":"choices",
      "collection": "gender",
      "order": 3
    },

    {
      "name":"year_started",
      "label":"Year began working as CHA or CHSS",
      "required":true,
      "helper_text":"Introduce the four digit year",
      "type":"int",
      "order": 4
    }
  ],

  "collections": [
    {
      "collection_name": "roles",
      "items":[
        {"id": "CHA", "value":"CHA"},
        {"id": "CHSS", "value":"CHSS"},
        {"id": "other", "value":"Other"}
      ]
    },

    {
      "collection_name": "gender",
      "items": [
        {"id": "male", "value":"Male"},
        {"id": "female", "value":"Female"},
        {"id": "other", "value":"Other"}
      ]
    }
  ],

  "register_steps": [
    {
      "order": 1,
      "title":"First step",
      "helper_text":"Please select your role",
      "fields":[
        {"name":"role", "order":1 },
        {"name":"role_other", "order":2 }
      ]
    },

    {
      "order": 2,
      "title":"Personal info",
      "helper_text":"Introduce your personal info (all fields required)",
      "conditional_byfield":"role",
      "conditional_byvalue":"!other",
      "fields":[
        "first_name",
        "last_name",
        "gender"
      ]
    },

    {
      "order": 2,
      "title":"Personal info",
      "conditional_byfield":"role",
      "conditional_byvalue":"!other",
      "helper_text":"Introduce your basic info",
      "fields":[
        "first_name",
        "last_name",
        "email"
      ]
    }
  ]
}